odoo/addons/sale_commission_check_deposit/README.rst
odoo/addons/sale_commission_check_deposit/__init__.py
odoo/addons/sale_commission_check_deposit/__manifest__.py
odoo/addons/sale_commission_check_deposit/i18n/es.po
odoo/addons/sale_commission_check_deposit/i18n/it.po
odoo/addons/sale_commission_check_deposit/i18n/sale_commission_check_deposit.pot
odoo/addons/sale_commission_check_deposit/models/__init__.py
odoo/addons/sale_commission_check_deposit/models/account_journal.py
odoo/addons/sale_commission_check_deposit/readme/CONTRIBUTORS.rst
odoo/addons/sale_commission_check_deposit/readme/DESCRIPTION.rst
odoo/addons/sale_commission_check_deposit/readme/USAGE.rst
odoo/addons/sale_commission_check_deposit/static/description/icon.png
odoo/addons/sale_commission_check_deposit/static/description/index.html
odoo/addons/sale_commission_check_deposit/views/account_journal_view.xml
odoo/addons/sale_commission_check_deposit/wizard/__init__.py
odoo/addons/sale_commission_check_deposit/wizard/wizard_check_settle.py
odoo14_addon_sale_commission_check_deposit-14.0.1.0.2.dist-info/METADATA
odoo14_addon_sale_commission_check_deposit-14.0.1.0.2.dist-info/WHEEL
odoo14_addon_sale_commission_check_deposit-14.0.1.0.2.dist-info/top_level.txt
odoo14_addon_sale_commission_check_deposit-14.0.1.0.2.dist-info/RECORD
